cd_proxy_manager/__init__.py
cd_proxy_manager/browser_judges.py
cd_proxy_manager/format_proxy.py
cd_proxy_manager/http_judges.py
cd_proxy_manager/my_private_proxies_api.py
cd_proxy_manager/proxy_dealer.py
cd_proxy_manager/set_env_proxy.py
cd_proxy_manager/set_global_proxy.py
cd_proxy_manager/version.py
cd_proxy_manager-0.2.6.dist-info/LICENSE.md
cd_proxy_manager-0.2.6.dist-info/LICENSE.txt
cd_proxy_manager-0.2.6.dist-info/METADATA
cd_proxy_manager-0.2.6.dist-info/WHEEL
cd_proxy_manager-0.2.6.dist-info/RECORD
