Metadata-Version: 2.1
Name: cd-proxy-manager
Version: 0.2.6
Summary: Manages proxies for http or selenium and some common uses cases like random,cycle, or set env/sys proxy.
License: LICENSE.md
Author: Nicholas Capasso
Author-email: codedocta@gmail.com
Requires-Python: >=3.9,<4.0
Classifier: License :: Other/Proprietary License
Classifier: Programming Language :: Python :: 3
Classifier: Programming Language :: Python :: 3.9
Classifier: Programming Language :: Python :: 3.10
Classifier: Programming Language :: Python :: 3.11
Classifier: Programming Language :: Python :: 3.12
Requires-Dist: requests (>=2.32.3,<3.0.0)
